LICENSE
README.md
setup.py
mines_market/__init__.py
mines_market/api_functions.py
mines_market/example.py
mines_market/menu.py
mines_market.egg-info/PKG-INFO
mines_market.egg-info/SOURCES.txt
mines_market.egg-info/dependency_links.txt
mines_market.egg-info/requires.txt
mines_market.egg-info/top_level.txt