Metadata-Version: 2.1
Name: mines-market
Version: 0.1.0
Summary: Access sodexo api to retrieve menu for desired location
Author: Yamato Matsumura, Keenan Buckley
Author-email: matsumura.yamato@gmail.com, keenandbuckley@protonmail.com
Classifier: Programming Language :: Python :: 3
Classifier: License :: OSI Approved :: BSD License
Classifier: Operating System :: OS Independent
Requires-Python: >=3.10
License-File: LICENSE
